README.rst
setup.py
data_validator/__init__.py
data_validator/exceptions.py
data_validator/unexpected.py
data_validator/validator.py
data_validator.egg-info/PKG-INFO
data_validator.egg-info/SOURCES.txt
data_validator.egg-info/dependency_links.txt
data_validator.egg-info/not-zip-safe
data_validator.egg-info/requires.txt
data_validator.egg-info/top_level.txt
data_validator/validators/__init__.py
data_validator/validators/base.py
data_validator/validators/length.py
data_validator/validators/regex.py
data_validator/validators/types.py
data_validator/validators/variants.py
examples/__init__.py
examples/test_task.py
examples/validate_user.py
examples/validate_user_.py