Metadata-Version: 1.0
Name: data-validator
Version: 0.1.2
Summary: 'Package for validate'
Home-page: https://github.com/moelius/data-validator
Author: Klimov Konstantin
Author-email: moelius1983@gmail.com
License: BSD
Platform: UNKNOWN
